tle_sat/__init__.py
tle_sat/algebra.py
tle_sat/algebra_test.py
tle_sat/cli.py
tle_sat/conftest.py
tle_sat/satellite.py
tle_sat/satellite_test.py
tle_sat-0.8.7.dist-info/METADATA
tle_sat-0.8.7.dist-info/WHEEL
tle_sat-0.8.7.dist-info/entry_points.txt
tle_sat-0.8.7.dist-info/RECORD
